README.md
setup.py
pooled_multiprocessing/__init__.py
pooled_multiprocessing/waiter.py
pooled_multiprocessing.egg-info/PKG-INFO
pooled_multiprocessing.egg-info/SOURCES.txt
pooled_multiprocessing.egg-info/dependency_links.txt
pooled_multiprocessing.egg-info/requires.txt
pooled_multiprocessing.egg-info/top_level.txt