Metadata-Version: 1.1
Name: pooled-multiprocessing
Version: 0.0.6
Summary: Simple pooled multiprocessing
Home-page: https://github.com/namuyan/pooled_multiprocessing
Author: namuyan
Author-email: UNKNOWN
License: MIT Licence
Platform: UNKNOWN
Classifier: Programming Language :: Python :: 3
Classifier: License :: OSI Approved :: MIT License
